{
  "required": true,
  "compatibilityLevel": "JAVA_8",
  "package": "me.lyric.infinity.mixin.mixins",
  "refmap": "mixins.solaros.refmap.json",
  "mixins": [
    "accessors.ICPacketPlayer",
    "accessors.IEntity",
    "accessors.IEntityPlayerSP",
    "accessors.IBlock",
    "accessors.ISPacketChat",
    "accessors.IEntityLivingBase",
    "blocks.MixinBlockLiquid",
    "entity.MixinEntityOtherPlayerMP",
    "entity.MixinEntityPlayerSP",
    "entity.MixinEntity",
    "entity.MixinEntityRenderer",
    "entity.MixinEntityLivingBase",
    "gui.MixinGuiIngame",
    "gui.MixinGuiNewChat",
    "network.MixinNetworkManager",
    "render.MixinRenderEnderCrystal",
    "render.MixinRenderLivingBase",
    "render.MixinLayerArmorBase"
  ]
}